taskin_types/__init__.py
taskin_types-1.0.5.dist-info/METADATA
taskin_types-1.0.5.dist-info/WHEEL
taskin_types-1.0.5.dist-info/RECORD
